{"altmetric_id": 94374200, "counts": {"readers": {"citeulike": "0", "mendeley": "33", "connotea": "0"}, "total": {"posts_count": 7}, "twitter": {"unique_users_count": 6, "posts_count": 7}}, "citation": {"altmetric_jid": "medrxiv", "authors": ["Zou, Canruo", "Wang, Xueting", "Xie, Zidian", "Li, Dongmei"], "doi": "10.1101/2020.07.25.20162024", "first_seen_on": "2020-11-16T11:17:35+00:00", "issns": [], "last_mentioned_on": 1597010373, "links": ["https://www.medrxiv.org/content/10.1101/2020.07.25.20162024v1", "https://pubmed.ncbi.nlm.nih.gov/32766599/?dopt=Abstract&utm_source=dlvr.it&utm_medium=twitter", "https://www.medrxiv.org/content/10.1101/2020.07.25.20162024v1?rss=1%22"], "pdf_url": "https://www.medrxiv.org/content/medrxiv/early/2020/07/28/2020.07.25.20162024.full.pdf", "pmid": "32766599", "publisher": "Cold Spring Harbor Laboratory", "title": "Public Reactions towards the COVID-19 Pandemic on Twitter in the United Kingdom and the United States", "type": "article", "mendeley_url": "https://www.mendeley.com/catalogue/6c5ce9cb-ecc9-3552-a676-41229ab2af6f/"}, "altmetric_score": {"score": 2.25, "score_history": {"1y": 2.25, "6m": 0, "3m": 0, "1m": 0, "1w": 0, "6d": 0, "5d": 0, "4d": 0, "3d": 0, "2d": 0, "1d": 0, "at": 2.25}, "context_for_score": {"all": {"total_number_of_other_articles": 16791453, "mean": 9.2911781045963, "rank": 9130914, "this_scored_higher_than_pct": 45, "this_scored_higher_than": 7558572, "rank_type": "exact", "sample_size": 16791453, "percentile": 45}, "similar_age_3m": {"total_number_of_other_articles": 319866, "mean": 16.477688663377, "rank": 146286, "this_scored_higher_than_pct": 53, "this_scored_higher_than": 170647, "rank_type": "exact", "sample_size": 319866, "percentile": 53}, "this_journal": {"total_number_of_other_articles": 16308, "mean": 54.355860436595, "rank": 9323, "this_scored_higher_than_pct": 40, "this_scored_higher_than": 6607, "rank_type": "exact", "sample_size": 16308, "percentile": 40}, "similar_age_this_journal_3m": {"total_number_of_other_articles": 2107, "mean": 59.177781680114, "rank": 1254, "this_scored_higher_than_pct": 38, "this_scored_higher_than": 811, "rank_type": "exact", "sample_size": 2107, "percentile": 38}}}, "demographics": {"poster_types": {"member_of_the_public": 5, "researcher": 1}, "users": {"twitter": {"cohorts": {"Members of the public": 5, "Scientists": 1}}, "mendeley": {"by_status": {"Professor > Associate Professor": 1, "Researcher": 3, "Student  > Master": 3, "Student  > Ph. D. Student": 2, "Student  > Bachelor": 4, "Student  > Doctoral Student": 2, "Lecturer": 4, "Other": 4, "Librarian": 2, "Unspecified": 1}, "by_discipline": {"Medicine and Dentistry": 10, "Social Sciences": 2, "Decision Sciences": 1, "Earth and Planetary Sciences": 1, "Psychology": 1, "Economics, Econometrics and Finance": 1, "Computer Science": 4, "Nursing and Health Professions": 2, "Biochemistry, Genetics and Molecular Biology": 1, "Environmental Science": 1, "Unspecified": 1}}}, "geo": {"twitter": {"US": 3}}}, "posts": {"twitter": [{"license": "gnip", "citation_ids": [94374200], "author": {"tweeter_id": "921400462838042624"}, "tweet_id": "1288077478213410816"}, {"license": "gnip", "citation_ids": [94374200], "author": {"tweeter_id": "1265336030833422337"}, "tweet_id": "1288205859265208320"}, {"license": "gnip", "citation_ids": [94374200], "author": {"tweeter_id": "36051159"}, "tweet_id": "1288212760564846594"}, {"license": "gnip", "citation_ids": [94374200], "author": {"tweeter_id": "1244711417657376768"}, "tweet_id": "1288307002582749185"}, {"license": "gnip", "citation_ids": [94374200], "author": {"tweeter_id": "4901919879"}, "tweet_id": "1288440843544690690"}, {"license": "gnip", "citation_ids": [94374200], "author": {"tweeter_id": "4901919879"}, "tweet_id": "1288440865262907393"}, {"license": "gnip", "citation_ids": [94374200], "author": {"tweeter_id": "297626036"}, "tweet_id": "1292581306061078528"}]}, "score": 2.25, "images": {"small": "https://badges.altmetric.com/?size=64&score=3&types=tttttttt", "medium": "https://badges.altmetric.com/?size=100&score=3&types=tttttttt", "large": "https://badges.altmetric.com/?size=180&score=3&types=tttttttt"}}