{"altmetric_id": 94382609, "counts": {"readers": {"citeulike": "0", "mendeley": "24", "connotea": "0"}, "total": {"posts_count": 4}, "twitter": {"unique_users_count": 4, "posts_count": 4}}, "citation": {"altmetric_jid": "medrxiv", "authors": ["Rathnasinghe, Raveen", "Karlicek, Robert F.", "Schotsaert, Michael", "Koffas, Mattheos", "Arduini, Brigitte", "Jangra, Sonia", "Wang, Bowen", "Davis, Jason L.", "Alnaggar, Mohammed", "Costa, Anthony", "Vincent, Richard", "Garcia-Sastre, Adolfo", "Vashishth, Deepak", "Balchandani, Priti"], "doi": "10.1101/2020.10.05.20206953", "first_seen_on": "2020-11-16T12:53:07+00:00", "issns": [], "last_mentioned_on": 1603366542, "links": ["https://www.medrxiv.org/content/10.1101/2020.10.05.20206953v1?rss=1%22", "https://www.medrxiv.org/content/10.1101/2020.10.05.20206953v1", "http://medrxiv.org/lookup/doi/10.1101/2020.10.05.20206953"], "pdf_url": "https://www.medrxiv.org/content/medrxiv/early/2020/10/06/2020.10.05.20206953.full.pdf", "publisher": "Cold Spring Harbor Laboratory", "title": "Scalable, effective, and rapid decontamination of SARS-CoV-2 contaminated N95 respirators using germicidal ultra-violet C (UVC) irradiation device", "type": "article", "mendeley_url": "https://www.mendeley.com/catalogue/1b04e161-b2b1-3afc-85dc-3defc34ba7ea/"}, "altmetric_score": {"score": 1.75, "score_history": {"1y": 1.75, "6m": 0, "3m": 0, "1m": 0, "1w": 0, "6d": 0, "5d": 0, "4d": 0, "3d": 0, "2d": 0, "1d": 0, "at": 1.75}, "context_for_score": {"all": {"total_number_of_other_articles": 17489191, "mean": 9.3996966964334, "rank": 10242730, "this_scored_higher_than_pct": 40, "this_scored_higher_than": 7078980, "rank_type": "exact", "sample_size": 17489191, "percentile": 40}, "similar_age_3m": {"total_number_of_other_articles": 321834, "mean": 16.687527321538, "rank": 165271, "this_scored_higher_than_pct": 47, "this_scored_higher_than": 151374, "rank_type": "exact", "sample_size": 321834, "percentile": 47}, "this_journal": {"total_number_of_other_articles": 19156, "mean": 55.121583942368, "rank": 11864, "this_scored_higher_than_pct": 35, "this_scored_higher_than": 6724, "rank_type": "exact", "sample_size": 19156, "percentile": 35}, "similar_age_this_journal_3m": {"total_number_of_other_articles": 2113, "mean": 65.450286796025, "rank": 1359, "this_scored_higher_than_pct": 33, "this_scored_higher_than": 707, "rank_type": "exact", "sample_size": 2113, "percentile": 33}}}, "demographics": {"poster_types": {"member_of_the_public": 4}, "users": {"twitter": {"cohorts": {"Members of the public": 4}}, "mendeley": {"by_status": {"Researcher": 3, "Student  > Master": 3, "Student  > Ph. D. Student": 1, "Student  > Bachelor": 3, "Other": 2, "Unspecified": 6}, "by_discipline": {"Medicine and Dentistry": 4, "Immunology and Microbiology": 1, "Agricultural and Biological Sciences": 2, "Nursing and Health Professions": 2, "Environmental Science": 1, "Unspecified": 7}}}, "geo": {"twitter": {"US": 1}}}, "posts": {"twitter": [{"license": "gnip", "citation_ids": [94382609], "author": {"tweeter_id": "1239643988707160064"}, "tweet_id": "1313484488052219908"}, {"license": "gnip", "citation_ids": [94382609], "author": {"tweeter_id": "1244711417657376768"}, "tweet_id": "1313676729135886336"}, {"license": "gnip", "citation_ids": [94382609], "author": {"tweeter_id": "1265336030833422337"}, "tweet_id": "1314429094239453184"}, {"license": "gnip", "citation_ids": [94382609], "author": {"tweeter_id": "4901919879"}, "tweet_id": "1319241014163443713"}]}, "score": 1.75, "images": {"small": "https://badges.altmetric.com/?size=64&score=2&types=tttttttt", "medium": "https://badges.altmetric.com/?size=100&score=2&types=tttttttt", "large": "https://badges.altmetric.com/?size=180&score=2&types=tttttttt"}}