{"altmetric_id": 83946069, "counts": {"readers": {"citeulike": "0", "mendeley": "86", "connotea": "0"}, "total": {"posts_count": 116}, "twitter": {"unique_users_count": 100, "posts_count": 114}, "blogs": {"unique_users_count": 1, "unique_users": [52417], "posts_count": 1}, "news": {"unique_users_count": 1, "unique_users": ["new_york_times"], "posts_count": 1}}, "citation": {"altmetric_jid": "532721422a83ee84788b4567", "authors": ["Iserman, Christiane", "Roden, Christine", "Boerneke, Mark", "Sealfon, Rachel", "McLaughlin, Grace", "Jungreis, Irwin", "Park, Chris", "Boppana, Avinash", "Fritch, Ethan", "Hou, Yixuan J.", "Theesfeld, Chandra", "Troyanskaya, Olga G", "Baric, Ralph S.", "Sheahan, Timothy P.", "Weeks, Kevin", "Gladfelter, Amy S."], "doi": "10.1101/2020.06.11.147199", "first_seen_on": "2020-06-13T05:04:12+00:00", "funders": ["niaid", "nci", "nigms", "nhlbi"], "issns": [], "journal": "bioRxiv", "last_mentioned_on": 1603158360, "links": ["https://www.biorxiv.org/content/10.1101/2020.06.11.147199v1", "https://www.biorxiv.org/content/10.1101/2020.06.11.147199v1.full.pdf", "https://doi.org/10.1101/2020.06.11.147199"], "pdf_url": "https://www.biorxiv.org/content/biorxiv/early/2020/06/12/2020.06.11.147199.full.pdf", "pmid": "32587965", "publisher": "Cold Spring Harbor Laboratory", "title": "Specific viral RNA drives the SARS CoV-2 nucleocapsid to phase separate", "type": "article", "mendeley_url": "https://www.mendeley.com/catalogue/360a2968-37f7-31a5-8ea6-7c07473b15ff/"}, "altmetric_score": {"score": 76.158, "score_history": {"1y": 66.158, "6m": 0, "3m": 0, "1m": 0, "1w": 0, "6d": 0, "5d": 0, "4d": 0, "3d": 0, "2d": 0, "1d": 0, "at": 76.158}, "context_for_score": {"all": {"total_number_of_other_articles": 17745665, "mean": 9.4504561400208, "rank": 339356, "this_scored_higher_than_pct": 98, "this_scored_higher_than": 17408209, "rank_type": "exact", "sample_size": 17745665, "percentile": 98}, "similar_age_3m": {"total_number_of_other_articles": 295645, "mean": 19.602355676571, "rank": 11912, "this_scored_higher_than_pct": 95, "this_scored_higher_than": 283746, "rank_type": "exact", "sample_size": 295645, "percentile": 95}, "this_journal": {"total_number_of_other_articles": 121541, "mean": 13.893306077785, "rank": 2464, "this_scored_higher_than_pct": 97, "this_scored_higher_than": 119087, "rank_type": "exact", "sample_size": 121541, "percentile": 97}, "similar_age_this_journal_3m": {"total_number_of_other_articles": 8634, "mean": 17.671813991198, "rank": 237, "this_scored_higher_than_pct": 97, "this_scored_higher_than": 8398, "rank_type": "exact", "sample_size": 8634, "percentile": 97}}}, "demographics": {"poster_types": {"member_of_the_public": 55, "researcher": 45}, "users": {"twitter": {"cohorts": {"Members of the public": 55, "Scientists": 45}}, "mendeley": {"by_status": {"Student  > Postgraduate": 2, "Professor > Associate Professor": 4, "Researcher": 22, "Student  > Master": 2, "Student  > Ph. D. Student": 14, "Professor": 5, "Student  > Bachelor": 10, "Student  > Doctoral Student": 2, "Lecturer": 1, "Other": 6, "Librarian": 1, "Unspecified": 2}, "by_discipline": {"Medicine and Dentistry": 11, "Social Sciences": 1, "Physics and Astronomy": 1, "Environmental Science": 1, "Unspecified": 2, "Chemical Engineering": 2, "Engineering": 1, "Chemistry": 2, "Neuroscience": 1, "Economics, Econometrics and Finance": 1, "Immunology and Microbiology": 7, "Agricultural and Biological Sciences": 11, "Linguistics": 1, "Biochemistry, Genetics and Molecular Biology": 22, "Veterinary Science and Veterinary Medicine": 2}}}, "geo": {"twitter": {"US": 31, "FR": 1, "NL": 1, "GB": 3, "IL": 2, "DE": 3, "MX": 1, "CA": 2, "ID": 1, "AU": 1, "CH": 1, "IN": 2, "PR": 1, "ES": 1, "AT": 1, "JP": 1}}}, "posts": {"twitter": [{"license": "gnip", "citation_ids": [83946069], "author": {"tweeter_id": "1949132852"}, "tweet_id": "1271661437879037952"}, {"license": "gnip", "citation_ids": [83946069], "author": {"tweeter_id": "85821611"}, "tweet_id": "1271662118127853575"}, {"license": "gnip", "citation_ids": [83946069], "author": {"tweeter_id": "3261777894"}, "tweet_id": "1271662601903185920"}, {"license": "gnip", "citation_ids": [83946069], "author": {"tweeter_id": "3398633772"}, "tweet_id": "1271670601128849408"}, {"license": "gnip", "citation_ids": [83946069], "author": {"tweeter_id": "1030562123456438273"}, "tweet_id": "1271688859361910784"}, {"license": "gnip", "citation_ids": [83946069], "author": {"tweeter_id": "3310961033"}, "tweet_id": "1271688906472329218"}, {"license": "gnip", "citation_ids": [83946069], "author": {"tweeter_id": "1055823957075681280"}, "tweet_id": "1271728087944888320"}, {"license": "gnip", "citation_ids": [83946069], "author": {"tweeter_id": "907134727"}, "tweet_id": "1271783859898777602"}, {"license": "gnip", "citation_ids": [83946069], "author": {"tweeter_id": "375307751"}, "tweet_id": "1271783919449526279"}, {"license": "gnip", "citation_ids": [83946069], "author": {"tweeter_id": "363320406"}, "tweet_id": "1271790464082026496"}, {"license": "gnip", "citation_ids": [83946069], "author": {"tweeter_id": "287146811"}, "tweet_id": "1271791248911642624"}, {"license": "gnip", "citation_ids": [83946069], "author": {"tweeter_id": "1146061838414733312"}, "tweet_id": "1271797008483979264"}, {"license": "gnip", "citation_ids": [83946069], "author": {"tweeter_id": "907134727"}, "tweet_id": "1271797170228924417"}, {"license": "gnip", "citation_ids": [83946069], "author": {"tweeter_id": "375307751"}, "tweet_id": "1271797287723859970"}, {"license": "gnip", "citation_ids": [83946069], "author": {"tweeter_id": "483122668"}, "tweet_id": "1271799357948428288"}, {"license": "gnip", "citation_ids": [83946069], "author": {"tweeter_id": "438095857"}, "tweet_id": "1271799529692676097"}, {"license": "gnip", "citation_ids": [83946069], "author": {"tweeter_id": "474088050"}, "tweet_id": "1271800650838523904"}, {"license": "gnip", "citation_ids": [83946069], "author": {"tweeter_id": "4091755695"}, "tweet_id": "1271801518589571074"}, {"license": "gnip", "citation_ids": [83946069], "author": {"tweeter_id": "938350616"}, "tweet_id": "1271801659191111684"}, {"license": "gnip", "citation_ids": [83946069], "author": {"tweeter_id": "922546872090316800"}, "tweet_id": "1271802169738608642"}, {"license": "gnip", "citation_ids": [83946069], "author": {"tweeter_id": "1068104833666830337"}, "tweet_id": "1271802476824612865"}, {"license": "gnip", "citation_ids": [83946069], "author": {"tweeter_id": "2378073328"}, "tweet_id": "1271803929752244229"}, {"license": "gnip", "citation_ids": [83946069], "author": {"tweeter_id": "38892114"}, "tweet_id": "1271806678799966210"}, {"license": "gnip", "citation_ids": [83946069], "author": {"tweeter_id": "830451647851618305"}, "tweet_id": "1271811889442418698"}, {"license": "gnip", "citation_ids": [83946069], "author": {"tweeter_id": "886990202157187072"}, "tweet_id": "1271814005963862017"}, {"license": "gnip", "citation_ids": [83946069], "author": {"tweeter_id": "724747069"}, "tweet_id": "1271814407421677573"}, {"license": "gnip", "citation_ids": [83946069], "author": {"tweeter_id": "126497051"}, "tweet_id": "1271816726943092736"}, {"license": "gnip", "citation_ids": [83946069], "author": {"tweeter_id": "931179725694914561"}, "tweet_id": "1271840218233135105"}, {"license": "gnip", "citation_ids": [83946069], "author": {"tweeter_id": "933202173403348993"}, "tweet_id": "1271840520516636672"}, {"license": "gnip", "citation_ids": [83946069], "author": {"tweeter_id": "180681534"}, "tweet_id": "1271842414081142784"}, {"license": "gnip", "citation_ids": [83946069], "author": {"tweeter_id": "752695412809662464"}, "tweet_id": "1271843537513054216"}, {"license": "gnip", "citation_ids": [83946069], "author": {"tweeter_id": "392157134"}, "tweet_id": "1271843747546816513"}, {"license": "gnip", "citation_ids": [83946069], "author": {"tweeter_id": "7248362"}, "tweet_id": "1271845146028630016"}, {"license": "gnip", "citation_ids": [83946069], "author": {"tweeter_id": "6107302"}, "tweet_id": "1271848432404070401"}, {"license": "gnip", "citation_ids": [83946069], "author": {"tweeter_id": "726386127867760641"}, "tweet_id": "1271857747336687616"}, {"license": "gnip", "citation_ids": [83946069], "author": {"tweeter_id": "1055823957075681280"}, "tweet_id": "1271862496949948421"}, {"license": "gnip", "citation_ids": [83946069], "author": {"tweeter_id": "3284292656"}, "tweet_id": "1271864693146005504"}, {"license": "gnip", "citation_ids": [83946069], "author": {"tweeter_id": "998989759920910336"}, "tweet_id": "1271864780006076422"}, {"license": "gnip", "citation_ids": [83946069], "author": {"tweeter_id": "2453279804"}, "tweet_id": "1271879230603788289"}, {"license": "gnip", "citation_ids": [83946069], "author": {"tweeter_id": "217963801"}, "tweet_id": "1271888218540081155"}, {"license": "gnip", "citation_ids": [83946069], "author": {"tweeter_id": "483122668"}, "tweet_id": "1271894755794976768"}, {"license": "gnip", "citation_ids": [83946069], "author": {"tweeter_id": "1223279285902946305"}, "tweet_id": "1271896567256145920"}, {"license": "gnip", "citation_ids": [83946069], "author": {"tweeter_id": "1212241349287612416"}, "tweet_id": "1271904734119473152"}, {"license": "gnip", "citation_ids": [83946069], "author": {"tweeter_id": "173832312"}, "tweet_id": "1271906450391121920"}, {"license": "gnip", "citation_ids": [83946069], "author": {"tweeter_id": "478761898"}, "tweet_id": "1271908054070702081"}, {"license": "gnip", "citation_ids": [83946069], "author": {"tweeter_id": "908985551818072064"}, "tweet_id": "1271912897778597888"}, {"license": "gnip", "citation_ids": [83946069], "author": {"tweeter_id": "867310057028845570"}, "tweet_id": "1271927292864815104"}, {"license": "gnip", "citation_ids": [83946069], "author": {"tweeter_id": "4091755695"}, "tweet_id": "1271937543060230145"}, {"license": "gnip", "citation_ids": [83946069], "author": {"tweeter_id": "3010730542"}, "tweet_id": "1271938367614304256"}, {"license": "gnip", "citation_ids": [83946069], "author": {"tweeter_id": "2922201803"}, "tweet_id": "1271942193696116742"}, {"license": "gnip", "citation_ids": [83946069], "author": {"tweeter_id": "970889678575431680"}, "tweet_id": "1271950123841417216"}, {"license": "gnip", "citation_ids": [83946069], "author": {"tweeter_id": "904547933613420544"}, "tweet_id": "1271956654515519488"}, {"license": "gnip", "citation_ids": [83946069], "author": {"tweeter_id": "2504618876"}, "tweet_id": "1271959866475638785"}, {"license": "gnip", "citation_ids": [83946069], "author": {"tweeter_id": "897561241383841798"}, "tweet_id": "1271967146541752321"}, {"license": "gnip", "citation_ids": [83946069], "author": {"tweeter_id": "980982922315550720"}, "tweet_id": "1271969748818055174"}, {"license": "gnip", "citation_ids": [83946069], "author": {"tweeter_id": "980982922315550720"}, "tweet_id": "1271969972714176512"}, {"license": "gnip", "citation_ids": [83946069], "author": {"tweeter_id": "3770391"}, "tweet_id": "1271974959645065218"}, {"license": "gnip", "citation_ids": [83946069], "author": {"tweeter_id": "1182439589094612998"}, "tweet_id": "1271977251052150791"}, {"license": "gnip", "citation_ids": [83946069], "author": {"tweeter_id": "1244711417657376768"}, "tweet_id": "1271989416341524482"}, {"license": "gnip", "citation_ids": [83946069], "author": {"tweeter_id": "730645657627860993"}, "tweet_id": "1271996359386644481"}, {"license": "gnip", "citation_ids": [83946069], "author": {"tweeter_id": "742197975577985024"}, "tweet_id": "1271997204681691136"}, {"license": "gnip", "citation_ids": [83946069], "author": {"tweeter_id": "14324284"}, "tweet_id": "1271999062179368961"}, {"license": "gnip", "citation_ids": [83946069], "author": {"tweeter_id": "78970944"}, "tweet_id": "1271999795067043842"}, {"license": "gnip", "citation_ids": [83946069], "author": {"tweeter_id": "1185048347230425088"}, "tweet_id": "1272029574713372672"}, {"license": "gnip", "citation_ids": [83946069], "author": {"tweeter_id": "365388250"}, "tweet_id": "1272066923182858241"}, {"license": "gnip", "citation_ids": [83946069], "author": {"tweeter_id": "1513318380"}, "tweet_id": "1272070237496782849"}, {"license": "gnip", "citation_ids": [83946069], "author": {"tweeter_id": "85319022"}, "tweet_id": "1272074057161244672"}, {"license": "gnip", "citation_ids": [83946069], "author": {"tweeter_id": "16967039"}, "tweet_id": "1272095524808687618"}, {"license": "gnip", "citation_ids": [83946069], "author": {"tweeter_id": "2680341006"}, "tweet_id": "1272211565274525699"}, {"license": "gnip", "citation_ids": [83946069], "author": {"tweeter_id": "19340281"}, "tweet_id": "1272221755243888640"}, {"license": "gnip", "citation_ids": [83946069], "author": {"tweeter_id": "3722321596"}, "tweet_id": "1272230642810597377"}, {"license": "gnip", "citation_ids": [83946069], "author": {"tweeter_id": "3862027438"}, "tweet_id": "1272256375171821568"}, {"license": "gnip", "citation_ids": [83946069], "author": {"tweeter_id": "1265336030833422337"}, "tweet_id": "1272287043532410880"}, {"license": "gnip", "citation_ids": [83946069], "author": {"tweeter_id": "3304508022"}, "tweet_id": "1272362042314199040"}, {"license": "gnip", "citation_ids": [83946069], "author": {"tweeter_id": "1271336113756614656"}, "tweet_id": "1272426996505743360"}, {"license": "gnip", "citation_ids": [83946069], "author": {"tweeter_id": "1257703653726699526"}, "tweet_id": "1272517309840621574"}, {"license": "gnip", "citation_ids": [83946069], "author": {"tweeter_id": "1166891694765355009"}, "tweet_id": "1273069502675267584"}, {"license": "gnip", "citation_ids": [83946069], "author": {"tweeter_id": "1273276757785919489"}, "tweet_id": "1273305991912792064"}, {"license": "gnip", "citation_ids": [83946069], "author": {"tweeter_id": "780502549422084096"}, "tweet_id": "1273994061595238401"}, {"license": "gnip", "citation_ids": [83946069], "author": {"tweeter_id": "2188835137"}, "tweet_id": "1273994586852032512"}, {"license": "gnip", "citation_ids": [83946069], "author": {"tweeter_id": "859006024707190787"}, "tweet_id": "1273998140383748096"}, {"license": "gnip", "citation_ids": [83946069], "author": {"tweeter_id": "768576066395013120"}, "tweet_id": "1274001539737124865"}, {"license": "gnip", "citation_ids": [83946069], "author": {"tweeter_id": "1163853743374290945"}, "tweet_id": "1274040827564744704"}, {"license": "gnip", "citation_ids": [83946069], "author": {"tweeter_id": "1099772502820208645"}, "tweet_id": "1274046078644617216"}, {"license": "gnip", "citation_ids": [83946069], "author": {"tweeter_id": "1122611886875262976"}, "tweet_id": "1274209775748657152"}, {"license": "gnip", "citation_ids": [83946069], "author": {"tweeter_id": "3496722194"}, "tweet_id": "1274246919863369728"}, {"license": "gnip", "citation_ids": [83946069], "author": {"tweeter_id": "2395444820"}, "tweet_id": "1274277089483485184"}, {"license": "gnip", "citation_ids": [83946069], "author": {"tweeter_id": "2561397751"}, "tweet_id": "1274296159562076165"}, {"license": "gnip", "citation_ids": [83946069], "author": {"tweeter_id": "2936666084"}, "tweet_id": "1274362816959414277"}, {"license": "gnip", "citation_ids": [83946069], "author": {"tweeter_id": "225968641"}, "tweet_id": "1275189381964447744"}, {"license": "gnip", "citation_ids": [83946069], "author": {"tweeter_id": "225968641"}, "tweet_id": "1275194011028828160"}, {"license": "gnip", "citation_ids": [83946069], "author": {"tweeter_id": "225968641"}, "tweet_id": "1275196732465430532"}, {"license": "gnip", "citation_ids": [83946069], "author": {"tweeter_id": "4901919879"}, "tweet_id": "1280304368483524610"}, {"license": "gnip", "citation_ids": [83946069], "author": {"tweeter_id": "4901919879"}, "tweet_id": "1280304390079905792"}, {"license": "gnip", "citation_ids": [83946069], "author": {"tweeter_id": "92527090"}, "tweet_id": "1281967587887157250"}, {"license": "gnip", "citation_ids": [83946069], "author": {"tweeter_id": "1007111191028645889"}, "tweet_id": "1281967921820917760"}, {"license": "gnip", "citation_ids": [83946069], "author": {"tweeter_id": "2943003366"}, "tweet_id": "1281968849210847234"}, {"license": "gnip", "citation_ids": [83946069, 84280334], "author": {"tweeter_id": "14496158"}, "tweet_id": "1281969722519506944"}, {"license": "gnip", "citation_ids": [83946069], "author": {"tweeter_id": "1178651803820285954"}, "tweet_id": "1281970201186070528"}, {"license": "gnip", "citation_ids": [83946069], "author": {"tweeter_id": "726386127867760641"}, "tweet_id": "1281970765881982984"}, {"license": "gnip", "citation_ids": [83946069], "author": {"tweeter_id": "726386127867760641"}, "tweet_id": "1281971726352388096"}, {"license": "gnip", "citation_ids": [83946069, 84280334], "author": {"tweeter_id": "92527090"}, "tweet_id": "1281977707912257536"}, {"license": "gnip", "citation_ids": [83946069, 84280334], "author": {"tweeter_id": "1178651803820285954"}, "tweet_id": "1281978060632469504"}, {"license": "gnip", "citation_ids": [83946069, 84280334], "author": {"tweeter_id": "200884295"}, "tweet_id": "1281980165308866561"}, {"license": "gnip", "citation_ids": [83946069], "author": {"tweeter_id": "367635500"}, "tweet_id": "1281980654817669122"}, {"license": "gnip", "citation_ids": [83946069, 84280334], "author": {"tweeter_id": "1007111191028645889"}, "tweet_id": "1281987915933835266"}, {"license": "gnip", "citation_ids": [83946069], "author": {"tweeter_id": "2298634046"}, "tweet_id": "1282066871886336000"}, {"license": "gnip", "citation_ids": [83946069, 84280334], "author": {"tweeter_id": "4730793972"}, "tweet_id": "1282123717930135553"}, {"license": "gnip", "citation_ids": [83946069], "author": {"tweeter_id": "994810769182220288"}, "tweet_id": "1282168919814361088"}, {"license": "gnip", "citation_ids": [83946069], "author": {"tweeter_id": "2937959582"}, "tweet_id": "1282212771141058566"}, {"license": "gnip", "citation_ids": [83946069], "author": {"tweeter_id": "896061493510193152"}, "tweet_id": "1282231848379092992"}, {"license": "gnip", "citation_ids": [83946069], "author": {"tweeter_id": "301348889"}, "tweet_id": "1282623064153313280"}, {"license": "gnip", "citation_ids": [85931246, 83946069], "author": {"tweeter_id": "938261382188945410"}, "tweet_id": "1293662505903030273"}, {"license": "gnip", "citation_ids": [83946069], "author": {"tweeter_id": "774245093045706752"}, "tweet_id": "1296308312787492864"}], "blogs": [{"title": "The physics of the SARS-CoV-2 virion", "url": "https://condensedconcepts.blogspot.com/2020/10/the-physics-of-sars-cov-2-virion.html", "license": "public", "citation_ids": [92710364, 84584985, 3367761, 83946069, 85698363, 88454218, 88454218, 88454218, 88454218, 88454218, 88454218, 88454218, 88454218, 88454218, 88454218, 88454218, 88454218, 88454218, 88454218, 88454218, 88454218, 88454218, 88454218, 88454218, 88454218, 88454218], "posted_on": "2020-10-20T01:46:00+00:00", "summary": "&nbsp;Some progress is being made in understanding the structure and dynamics of the SARS-CoV-2 virions (virus particles) that are responsible for the pandemic. A nice starting point for the non-expert is a recent article in The New York Times.A fundamenta", "author": {"name": "Condensed concepts", "url": "http://condensedconcepts.blogspot.com/", "description": "Ruminations on emergent phenomena in condensed phases of matter"}}], "news": [{"title": "The Coronavirus Unveiled", "url": "https://www.nytimes.com/interactive/2020/health/coronavirus-unveiled.html", "license": "public", "citation_ids": [89626792, 88454218, 91045470, 88665084, 87801844, 83946069, 87191624, 89737107, 89705681], "posted_on": "2019-12-31T18:30:00+00:00", "summary": "In February, as the new coronavirus swept across China and shut down entire cities, a scientist named Sai Li set out to paint its portrait. At the time, the best pictures anyone had managed to take were low-resolution images, in which the virus looked like", "author": {"name": "New York Times", "url": "http://www.nytimes.com/", "image": "https://s3.amazonaws.com/weyland.altmetric.com/news_sources/logos/000/000/022/normal/image.png?1369859672"}}]}, "score": 76.158, "images": {"small": "https://badges.altmetric.com/?size=64&score=77&types=mbtttttt", "medium": "https://badges.altmetric.com/?size=100&score=77&types=mbtttttt", "large": "https://badges.altmetric.com/?size=180&score=77&types=mbtttttt"}}